.coveragerc
.travis.yml
AUTHORS
ChangeLog
LICENSE
MANIFEST.in
README.rst
requirements.txt
setup.cfg
setup.py
tox.ini
docs/Makefile
docs/make.bat
docs/source/conf.py
docs/source/index.rst
docs/source/readme.rst
leonardo_keeweb/__init__.py
leonardo_keeweb/urls.py
leonardo_keeweb/views.py
leonardo_keeweb.egg-info/PKG-INFO
leonardo_keeweb.egg-info/SOURCES.txt
leonardo_keeweb.egg-info/dependency_links.txt
leonardo_keeweb.egg-info/not-zip-safe
leonardo_keeweb.egg-info/pbr.json
leonardo_keeweb.egg-info/top_level.txt
leonardo_keeweb/apps/__init__.py
leonardo_keeweb/apps/keeweb.py
leonardo_keeweb/templates/.DS_Store
leonardo_keeweb/templates/keeweb.html
requirements/default.txt
requirements/tests.txt
tests/cov.sh
tests/local_settings.py
tests/manage.py
tests/testapp/__init__.py
tests/testapp/models.py
tests/testapp/settings.py
tests/testapp/urls.py
tests/testapp/tests/__init__.py
tests/testapp/tests/test_commands.py